{
    "backend": "api-server-nodejs",
    "db_name": "",
    "db_pass": "",
    "db_type": "sqlite",
    "db_user": "",
    "dbms": "1",
    "description": "generated product",
    "design": "soft-ui-dashboard",
    "docker": "1",
    "err_code": 0,
    "frontend": "react",
    "heroku": "0",
    "pattern": "fullstack",
    "pro": "0",
    "task_id": "8c520b49-7787-44fe-9ec5-f738697b886c",
    "task_info": "Upload Sources [0%] - 291 files",
    "task_output": "8c520b49-7787-44fe-9ec5-f738697b886c.zip",
    "task_result": "SUCCESS",
    "task_state": "RUNNING",
    "task_ts_end": "2024-10-08-12-34-13",
    "task_ts_start": "2024-10-08-12-34-11"
}